taxoniq_accession_lengths/__init__.py
taxoniq_accession_lengths/db.marisa
taxoniq_accession_lengths-2021.3.23.dist-info/METADATA
taxoniq_accession_lengths-2021.3.23.dist-info/WHEEL
taxoniq_accession_lengths-2021.3.23.dist-info/top_level.txt
taxoniq_accession_lengths-2021.3.23.dist-info/RECORD
